BaseAWS/__init__.py
BaseAWS/ami.py
BaseAWS/eb.py
BaseAWS/ec2.py
BaseAWS/eks.py
BaseAWS/elb.py
BaseAWS/helper.py
BaseAWS/rds.py
BaseAWS/security_group.py
BaseAWS/vpc.py
Xby2AWS-1.1.9.dist-info/LICENSE
Xby2AWS-1.1.9.dist-info/METADATA
Xby2AWS-1.1.9.dist-info/WHEEL
Xby2AWS-1.1.9.dist-info/entry_points.txt
Xby2AWS-1.1.9.dist-info/top_level.txt
Xby2AWS-1.1.9.dist-info/RECORD
