Metadata-Version: 2.1
Name: Xby2AWS
Version: 1.1.9
Summary: Allows for the creation of custom pulumi resources.
Author-email: Collin Whitlow <cwhitlow@xby2.com>
License: Copyright 2022 X by 2        
Keywords: pulumi,xby2,aws
Classifier: License :: OSI Approved :: MIT License
Classifier: Programming Language :: Python
Classifier: Programming Language :: Python :: 3
Requires-Python: >=3.8
License-File: LICENSE
Requires-Dist: pulumi (<4.0.0,>=3.0.0)
Requires-Dist: pulumi-aws (<6.0.0,>=5.0.0)
Requires-Dist: pulumi-awsx
